streamlit_login_auth_ui_zh/__init__.py
streamlit_login_auth_ui_zh/utils.py
streamlit_login_auth_ui_zh/widgets.py
streamlit_login_auth_ui_zh-0.1.3.dist-info/LICENSE
streamlit_login_auth_ui_zh-0.1.3.dist-info/METADATA
streamlit_login_auth_ui_zh-0.1.3.dist-info/WHEEL
streamlit_login_auth_ui_zh-0.1.3.dist-info/top_level.txt
streamlit_login_auth_ui_zh-0.1.3.dist-info/RECORD
