Metadata-Version: 2.1
Name: streamlit_login_auth_ui_zh
Version: 0.1.3
Summary: 这个库是一个用户友好的 Streamlit 登录/注册系统，基于streamlit_login_auth_ui 库改写构建。 它为开发者提供了一种简单的方法，以便在其 Streamlit 应用程序中实现安全的用户身份注册和验证。
Author: Rycen7822
Author-email: kristinharrison7826@gmail.com
Classifier: Programming Language :: Python :: 3
Classifier: License :: OSI Approved :: MIT License
Classifier: Operating System :: OS Independent
Requires-Python: >=3.6
License-File: LICENSE
